gimbal/__init__.py
gimbal/_version.py
gimbal/bonding.py
gimbal/constants.py
gimbal/displace.py
gimbal/fileio.py
gimbal/kabsch.py
gimbal/measure.py
gimbal/molecule.py
gimbal/substitute.py
gimbal/symmetry.py
gimbal-0.1.1.data/scripts/convgeom
gimbal-0.1.1.data/scripts/measure
gimbal-0.1.1.data/scripts/nudge
gimbal-0.1.1.data/scripts/subst
gimbal-0.1.1.dist-info/LICENSE
gimbal-0.1.1.dist-info/METADATA
gimbal-0.1.1.dist-info/WHEEL
gimbal-0.1.1.dist-info/top_level.txt
gimbal-0.1.1.dist-info/RECORD
