Metadata-Version: 2.1
Name: gimbal
Version: 0.1.1
Summary: Tools for importing, creating, editing and querying molecular geometries
Home-page: https://github.com/ryjmacdonell/gimbal
Author: Ryan J. MacDonell
Author-email: rmacd054@uottawa.ca
License: MIT
Keywords: gimbal molecule geometry displacement transformation 3D
Platform: UNKNOWN
Classifier: Development Status :: 3 - Alpha
Classifier: Environment :: Console
Classifier: Programming Language :: Python :: 3
Classifier: Programming Language :: Python :: 3.4
Classifier: Programming Language :: Python :: 3.5
Classifier: Programming Language :: Python :: 3.6
Classifier: Programming Language :: Python :: 3.7
Classifier: Topic :: Scientific/Engineering :: Chemistry
Requires-Dist: numpy (>=1.6.0)
Requires-Dist: scipy (>=0.9.0)
Requires-Dist: pyparsing (>=2.2.0)
